nc1709/__init__.py
nc1709/async_request_queue.py
nc1709/checkpoints.py
nc1709/cli.py
nc1709/cli_enhanced.py
nc1709/cli_ui.py
nc1709/config.py
nc1709/conversation_logger.py
nc1709/custom_commands.py
nc1709/exceptions.py
nc1709/executor.py
nc1709/file_controller.py
nc1709/git_integration.py
nc1709/github_integration.py
nc1709/image_input.py
nc1709/linting.py
nc1709/llm_adapter.py
nc1709/logger.py
nc1709/model_loader.py
nc1709/permission_ui.py
nc1709/plan_mode.py
nc1709/progress.py
nc1709/reasoning_engine.py
nc1709/remote_client.py
nc1709/request_queue.py
nc1709/requirements_tracker.py
nc1709/shell_completions.py
nc1709/slash_commands.py
nc1709/task_classifier.py
nc1709/telemetry.py
nc1709/thinking_messages.py
nc1709/tool_ui.py
nc1709/version_check.py
nc1709/agent/__init__.py
nc1709/agent/core.py
nc1709/agent/di_agent.py
nc1709/agent/mcp_bridge.py
nc1709/agent/permissions.py
nc1709/agent/refactored_agent.py
nc1709/agent/components/__init__.py
nc1709/agent/components/history_tracker.py
nc1709/agent/components/llm_interface.py
nc1709/agent/components/loop_detector.py
nc1709/agent/components/permission_manager.py
nc1709/agent/components/response_formatter.py
nc1709/agent/components/tool_executor.py
nc1709/agent/tools/__init__.py
nc1709/agent/tools/base.py
nc1709/agent/tools/bash_tool.py
nc1709/agent/tools/file_tools.py
nc1709/agent/tools/notebook_tools.py
nc1709/agent/tools/search_tools.py
nc1709/agent/tools/task_tool.py
nc1709/agent/tools/web_tools.py
nc1709/agents/__init__.py
nc1709/agents/auto_fix.py
nc1709/agents/test_generator.py
nc1709/cognitive/__init__.py
nc1709/cognitive/anticipation.py
nc1709/cognitive/context_engine.py
nc1709/cognitive/council.py
nc1709/cognitive/learning.py
nc1709/cognitive/router.py
nc1709/cognitive/system.py
nc1709/deepfabric/__init__.py
nc1709/deepfabric/core.py
nc1709/deepfabric/data_generator.py
nc1709/deepfabric/train.py
nc1709/di/__init__.py
nc1709/di/container.py
nc1709/di/decorators.py
nc1709/di/providers.py
nc1709/di/services.py
nc1709-3.0.31.dist-info/METADATA
nc1709-3.0.31.dist-info/WHEEL
nc1709-3.0.31.dist-info/entry_points.txt
nc1709-3.0.31.dist-info/top_level.txt
nc1709-3.0.31.dist-info/RECORD
