Metadata-Version: 2.4
Name: nc1709
Version: 3.0.31
Summary: AI coding assistant with fine-tuned tool calling - Your code comes to life
Home-page: https://github.com/lafzusa/nc1709
Author: Lafzusa Corp
Author-email: asif90988@gmail.com
Classifier: Development Status :: 4 - Beta
Classifier: Intended Audience :: Developers
Classifier: Topic :: Software Development :: Libraries :: Application Frameworks
Classifier: Topic :: Scientific/Engineering :: Artificial Intelligence
Classifier: License :: Other/Proprietary License
Classifier: Programming Language :: Python :: 3
Classifier: Programming Language :: Python :: 3.9
Classifier: Programming Language :: Python :: 3.10
Classifier: Programming Language :: Python :: 3.11
Classifier: Programming Language :: Python :: 3.12
Requires-Python: >=3.9
Requires-Dist: rich>=13.0.0
Requires-Dist: prompt_toolkit>=3.0.0
Requires-Dist: click>=8.1.0
Requires-Dist: pydantic>=2.0.0
Requires-Dist: python-dotenv>=0.20.0
Requires-Dist: httpx>=0.24.0
Requires-Dist: aiofiles>=23.0.0
Requires-Dist: psutil>=5.9.0
Requires-Dist: ddgs>=9.0.0
Provides-Extra: local
Requires-Dist: litellm>=1.0.0; extra == "local"
Requires-Dist: huggingface_hub>=0.20.0; extra == "local"
Requires-Dist: transformers>=4.36.0; extra == "local"
Requires-Dist: torch>=2.0.0; extra == "local"
Requires-Dist: accelerate>=0.25.0; extra == "local"
Requires-Dist: bitsandbytes>=0.41.0; extra == "local"
Requires-Dist: peft>=0.7.0; extra == "local"
Provides-Extra: server
Requires-Dist: prometheus-client>=0.17.0; extra == "server"
Requires-Dist: litellm>=1.0.0; extra == "server"
Provides-Extra: memory
Requires-Dist: chromadb>=0.4.0; extra == "memory"
Requires-Dist: sentence-transformers>=2.2.0; extra == "memory"
Provides-Extra: dev
Requires-Dist: pytest>=7.0.0; extra == "dev"
Requires-Dist: pytest-asyncio>=0.21.0; extra == "dev"
Requires-Dist: black>=23.0.0; extra == "dev"
Requires-Dist: mypy>=1.0.0; extra == "dev"
Provides-Extra: full
Requires-Dist: litellm>=1.0.0; extra == "full"
Requires-Dist: huggingface_hub>=0.20.0; extra == "full"
Requires-Dist: transformers>=4.36.0; extra == "full"
Requires-Dist: torch>=2.0.0; extra == "full"
Requires-Dist: accelerate>=0.25.0; extra == "full"
Requires-Dist: bitsandbytes>=0.41.0; extra == "full"
Requires-Dist: peft>=0.7.0; extra == "full"
Requires-Dist: prometheus-client>=0.17.0; extra == "full"
Requires-Dist: chromadb>=0.4.0; extra == "full"
Requires-Dist: sentence-transformers>=2.2.0; extra == "full"
Dynamic: author
Dynamic: author-email
Dynamic: classifier
Dynamic: description
Dynamic: description-content-type
Dynamic: home-page
Dynamic: provides-extra
Dynamic: requires-dist
Dynamic: requires-python
Dynamic: summary
